ctesiphon/__init__.py
ctesiphon/dbo/__init__.py
ctesiphon/dbo/base.py
ctesiphon/dbo/clickhouse.py
ctesiphon/dbo/rethinkdb.py
ctesiphon/drivers/__init__.py
ctesiphon/drivers/data/__init__.py
ctesiphon/drivers/data/base.py
ctesiphon/drivers/data/clickhouse.py
ctesiphon/drivers/data/rethinkdb.py
ctesiphon/dto/__init__.py
ctesiphon/dto/base.py
ctesiphon/enums/__init__.py
ctesiphon/enums/cache_types.py
ctesiphon/enums/condition_types.py
ctesiphon/interfaces/__init__.py
ctesiphon/interfaces/container.py
ctesiphon/interfaces/migrations.py
ctesiphon/modules/__init__.py
ctesiphon/modules/communications/__init__.py
ctesiphon/modules/communications/consumer/__init__.py
ctesiphon/modules/communications/consumer/emails.py
ctesiphon/modules/communications/consumer/router.py
ctesiphon/modules/communications/enums/__init__.py
ctesiphon/modules/communications/enums/email_statuses.py
ctesiphon/modules/communications/enums/email_types.py
ctesiphon/modules/communications/helpers/__init__.py
ctesiphon/modules/communications/helpers/create_email.py
ctesiphon/modules/communications/helpers/send_email.py
ctesiphon/modules/communications/interfaces/__init__.py
ctesiphon/modules/communications/interfaces/container.py
ctesiphon/modules/communications/interfaces/settings.py
ctesiphon/modules/communications/models/__init__.py
ctesiphon/modules/communications/models/email.py
ctesiphon/modules/communications/models/email_settings.py
ctesiphon/modules/communications/settings.py
ctesiphon/modules/healthcheck/__init__.py
ctesiphon/modules/healthcheck/api/__init__.py
ctesiphon/modules/healthcheck/api/db.py
ctesiphon/modules/healthcheck/api/router.py
ctesiphon/modules/healthcheck/errors.py
ctesiphon/repositories/__init__.py
ctesiphon/repositories/model.py
ctesiphon/services/__init__.py
ctesiphon/services/aiokafka_service.py
ctesiphon/services/fastapi_service.py
ctesiphon/settings/__init__.py
ctesiphon/settings/clickhouse.py
ctesiphon/settings/communications.py
ctesiphon/settings/files.py
ctesiphon-0.1.17.dist-info/LICENSE
ctesiphon-0.1.17.dist-info/METADATA
ctesiphon-0.1.17.dist-info/WHEEL
ctesiphon-0.1.17.dist-info/RECORD
